Metadata-Version: 1.1
Name: SES-Mailer
Version: 0.5.2
Summary: 
